image2pipe/FastVideoReader.py
image2pipe/Timer.py
image2pipe/__init__.py
image2pipe/ffmpeg.py
image2pipe/tensor.py
image2pipe/utils.py
image2pipe_nicholas_tancredi-0.2.2.dist-info/LICENSE.txt
image2pipe_nicholas_tancredi-0.2.2.dist-info/METADATA
image2pipe_nicholas_tancredi-0.2.2.dist-info/WHEEL
image2pipe_nicholas_tancredi-0.2.2.dist-info/top_level.txt
image2pipe_nicholas_tancredi-0.2.2.dist-info/RECORD
