Metadata-Version: 2.1
Name: image2pipe-nicholas-tancredi
Version: 0.2.2
Summary: Simple ffmpeg wrapper for image2pipe which yields rawvideo frames from input video URL
Home-page: UNKNOWN
Author: Nicholas Tancredi
License: LICENSE.txt
Keywords: ffmpeg yuv image2pipe
Platform: UNKNOWN
Requires-Python: >=3.2
Requires-Dist: tblib
Requires-Dist: numpy
Requires-Dist: websocket
